<?xml version="1.0" encoding="UTF-8"?> 
<databaseChangeLog 
  xmlns="http://www.liquibase.org/xml/ns/dbchangelog" 
  xmlns:xsi="http://www.w3.org/2001/XMLSchema-instance" 
  xsi:schemaLocation="http://www.liquibase.org/xml/ns/dbchangelog
  http://www.liquibase.org/xml/ns/dbchangelog/dbchangelog-2.0.xsd">

	<property name="tinyint.type"     value="tinyint" dbms="mysql"/>
	<property name="tinyint.type"     value="number(3, 0)" dbms="oracle"/>
	<property name="int.type"         value="bigint"         dbms="mysql"/>
	<property name="int.type"         value="number(19,0)"   dbms="oracle"/>
	<property name="text.type"        value="varchar(1000)"  dbms="mysql"/>
	<property name="text.type"        value="varchar2(1000)" dbms="oracle"/>
	<property name="clob.type"        value="clob"           dbms="oracle"/>
	<property name="clob.type"        value="longtext"       dbms="mysql"/>
	<property name="blob.type"        value="blob"           dbms="oracle"/>
	<property name="blob.type"        value="longblob"       dbms="mysql"/>
	<property name="string.type"      value="varchar"        dbms="mysql" />
	<property name="string.type"      value="varchar2"       dbms="oracle" />
	<property name="ts.type"          value="timestamp"      dbms="mysql" />
	<property name="ts.type"          value="timestamp"      dbms="oracle" />
	<property name="nullable.ts.type" value="timestamp null" dbms="mysql" />
	<property name="nullable.ts.type" value="timestamp"      dbms="oracle" />

	<property name="autoIncrement"    value="true"           dbms="mysql"/>
	<property name="autoIncrement"    value="false"          dbms="oracle"/>
</databaseChangeLog> 
